connect_four_game/__init__.py
connect_four_game/app/__init__.py
connect_four_game/app/setup_test_env.py
connect_four_game/app/utils.py
connect_four_game/app/agent/__init__.py
connect_four_game/app/agent/agent.py
connect_four_game/app/agent/base_agent.py
connect_four_game/app/agent/test_agent.py
connect_four_game/app/board/__init__.py
connect_four_game/app/board/board.py
connect_four_game/app/board/test_board.py
connect_four_game/app/board_evaluator/__init__.py
connect_four_game/app/board_evaluator/board_evaluator.py
connect_four_game/app/board_evaluator/test_board_evaluator.py
connect_four_game/app/lifecycle_manager/__init__.py
connect_four_game/app/lifecycle_manager/lifecycle_manager.py
connect_four_game-0.1.6.dist-info/LICENSE
connect_four_game-0.1.6.dist-info/METADATA
connect_four_game-0.1.6.dist-info/WHEEL
connect_four_game-0.1.6.dist-info/top_level.txt
connect_four_game-0.1.6.dist-info/RECORD
