Metadata-Version: 2.1
Name: connect-four-game
Version: 0.1.6
Summary: Example PyPI (Python Package Index) Package
Home-page: https://github.com/will-flemmer/connect-4
Author: Will Flemmer
Project-URL: Documentation, https://github.com/will-flemmer/connect-4
Project-URL: Bug Reports, https://github.com/will-flemmer/connect-4/issues
Project-URL: Source Code, https://github.com/will-flemmer/connect-4
Keywords: connect_four_game,pypi,package
Classifier: Development Status :: 5 - Production/Stable
Classifier: Intended Audience :: Developers
Classifier: Topic :: Software Development :: Build Tools
Classifier: Programming Language :: Python :: 3
Classifier: Programming Language :: Python :: 3.6
Classifier: Programming Language :: Python :: 3.7
Classifier: Programming Language :: Python :: 3.8
Classifier: Programming Language :: Python :: 3.9
Classifier: Programming Language :: Python :: 3 :: Only
Classifier: License :: OSI Approved :: MIT License
Classifier: Operating System :: OS Independent
Requires-Python: >=3.6
License-File: LICENSE
Provides-Extra: dev
Requires-Dist: check-manifest ; extra == 'dev'
